[
  {
    "date": "2024-04-03T21:30:39.264Z",
    "DAW_totalHonor": 3050,
    "DAW_totalScore": 3068,
    "DAM_totalHonor": 5234,
    "DAM_totalScore": 5156,
    "loosers_totalHonor": 1,
    "loosers_totalScore": 0
  },
  {
    "date": "2024-04-04T21:30:43.779Z",
    "DAW_totalHonor": 3060,
    "DAW_totalScore": 3079,
    "DAM_totalHonor": 5234,
    "DAM_totalScore": 5156,
    "loosers_totalHonor": 1,
    "loosers_totalScore": 0
  },
  {
    "date": "2024-04-05T21:30:57.606Z",
    "DAW_totalHonor": 3060,
    "DAW_totalScore": 3079,
    "DAM_totalHonor": 5234,
    "DAM_totalScore": 5156,
    "loosers_totalHonor": 1,
    "loosers_totalScore": 0
  },
  {
    "date": "2024-04-06T21:30:39.789Z",
    "DAW_totalHonor": 3060,
    "DAW_totalScore": 3079,
    "DAM_totalHonor": 5234,
    "DAM_totalScore": 5156,
    "loosers_totalHonor": 1,
    "loosers_totalScore": 0
  },
  {
    "date": "2024-04-07T21:30:39.627Z",
    "DAW_totalHonor": 3062,
    "DAW_totalScore": 3082,
    "DAM_totalHonor": 5234,
    "DAM_totalScore": 5156,
    "loosers_totalHonor": 1,
    "loosers_totalScore": 0
  },
  {
    "date": "2024-04-08T21:31:03.023Z",
    "DAW_totalHonor": 3068,
    "DAW_totalScore": 3089,
    "DAM_totalHonor": 5234,
    "DAM_totalScore": 5156,
    "loosers_totalHonor": 1,
    "loosers_totalScore": 0
  },
  {
    "date": "2024-04-09T21:30:57.733Z",
    "DAW_totalHonor": 3074,
    "DAW_totalScore": 3097,
    "DAM_totalHonor": 5234,
    "DAM_totalScore": 5156,
    "loosers_totalHonor": 1,
    "loosers_totalScore": 0
  }
]